{"ongoing_trials": {}, "hyperparameters": {"space": [{"class_name": "Int", "config": {"name": "num_layers", "default": null, "conditions": [], "min_value": 4, "max_value": 10, "step": 1, "sampling": "linear"}}, {"class_name": "Int", "config": {"name": "input_units", "default": null, "conditions": [], "min_value": 32, "max_value": 128, "step": 16, "sampling": "linear"}}, {"class_name": "Int", "config": {"name": "dense_units_0", "default": null, "conditions": [], "min_value": 32, "max_value": 128, "step": 16, "sampling": "linear"}}, {"class_name": "Choice", "config": {"name": "activation_0", "default": "relu", "conditions": [], "values": ["relu", "tanh", "sigmoid"], "ordered": false}}, {"class_name": "Float", "config": {"name": "dropout_rate_0", "default": 0.0, "conditions": [], "min_value": 0.0, "max_value": 0.5, "step": 0.1, "sampling": "linear"}}, {"class_name": "Int", "config": {"name": "dense_units_1", "default": null, "conditions": [], "min_value": 32, "max_value": 128, "step": 16, "sampling": "linear"}}, {"class_name": "Choice", "config": {"name": "activation_1", "default": "relu", "conditions": [], "values": ["relu", "tanh", "sigmoid"], "ordered": false}}, {"class_name": "Float", "config": {"name": "dropout_rate_1", "default": 0.0, "conditions": [], "min_value": 0.0, "max_value": 0.5, "step": 0.1, "sampling": "linear"}}, {"class_name": "Int", "config": {"name": "dense_units_2", "default": null, "conditions": [], "min_value": 32, "max_value": 128, "step": 16, "sampling": "linear"}}, {"class_name": "Choice", "config": {"name": "activation_2", "default": "relu", "conditions": [], "values": ["relu", "tanh", "sigmoid"], "ordered": false}}, {"class_name": "Float", "config": {"name": "dropout_rate_2", "default": 0.0, "conditions": [], "min_value": 0.0, "max_value": 0.5, "step": 0.1, "sampling": "linear"}}, {"class_name": "Choice", "config": {"name": "optimizer", "default": "adam", "conditions": [], "values": ["adam", "sgd", "rmsprop"], "ordered": false}}, {"class_name": "Int", "config": {"name": "dense_units_3", "default": null, "conditions": [], "min_value": 32, "max_value": 128, "step": 16, "sampling": "linear"}}, {"class_name": "Choice", "config": {"name": "activation_3", "default": "relu", "conditions": [], "values": ["relu", "tanh", "sigmoid"], "ordered": false}}, {"class_name": "Float", "config": {"name": "dropout_rate_3", "default": 0.0, "conditions": [], "min_value": 0.0, "max_value": 0.5, "step": 0.1, "sampling": "linear"}}, {"class_name": "Int", "config": {"name": "dense_units_4", "default": null, "conditions": [], "min_value": 32, "max_value": 128, "step": 16, "sampling": "linear"}}, {"class_name": "Choice", "config": {"name": "activation_4", "default": "relu", "conditions": [], "values": ["relu", "tanh", "sigmoid"], "ordered": false}}, {"class_name": "Float", "config": {"name": "dropout_rate_4", "default": 0.0, "conditions": [], "min_value": 0.0, "max_value": 0.5, "step": 0.1, "sampling": "linear"}}, {"class_name": "Int", "config": {"name": "dense_units_5", "default": null, "conditions": [], "min_value": 32, "max_value": 128, "step": 16, "sampling": "linear"}}, {"class_name": "Choice", "config": {"name": "activation_5", "default": "relu", "conditions": [], "values": ["relu", "tanh", "sigmoid"], "ordered": false}}, {"class_name": "Float", "config": {"name": "dropout_rate_5", "default": 0.0, "conditions": [], "min_value": 0.0, "max_value": 0.5, "step": 0.1, "sampling": "linear"}}, {"class_name": "Int", "config": {"name": "dense_units_6", "default": null, "conditions": [], "min_value": 32, "max_value": 128, "step": 16, "sampling": "linear"}}, {"class_name": "Choice", "config": {"name": "activation_6", "default": "relu", "conditions": [], "values": ["relu", "tanh", "sigmoid"], "ordered": false}}, {"class_name": "Float", "config": {"name": "dropout_rate_6", "default": 0.0, "conditions": [], "min_value": 0.0, "max_value": 0.5, "step": 0.1, "sampling": "linear"}}, {"class_name": "Int", "config": {"name": "dense_units_7", "default": null, "conditions": [], "min_value": 32, "max_value": 128, "step": 16, "sampling": "linear"}}, {"class_name": "Choice", "config": {"name": "activation_7", "default": "relu", "conditions": [], "values": ["relu", "tanh", "sigmoid"], "ordered": false}}, {"class_name": "Float", "config": {"name": "dropout_rate_7", "default": 0.0, "conditions": [], "min_value": 0.0, "max_value": 0.5, "step": 0.1, "sampling": "linear"}}, {"class_name": "Int", "config": {"name": "dense_units_8", "default": null, "conditions": [], "min_value": 32, "max_value": 128, "step": 16, "sampling": "linear"}}, {"class_name": "Choice", "config": {"name": "activation_8", "default": "relu", "conditions": [], "values": ["relu", "tanh", "sigmoid"], "ordered": false}}, {"class_name": "Float", "config": {"name": "dropout_rate_8", "default": 0.0, "conditions": [], "min_value": 0.0, "max_value": 0.5, "step": 0.1, "sampling": "linear"}}], "values": {"num_layers": 4, "input_units": 32, "dense_units_0": 32, "activation_0": "relu", "dropout_rate_0": 0.0, "dense_units_1": 32, "activation_1": "relu", "dropout_rate_1": 0.0, "dense_units_2": 32, "activation_2": "relu", "dropout_rate_2": 0.0, "optimizer": "adam", "dense_units_3": 32, "activation_3": "relu", "dropout_rate_3": 0.0, "dense_units_4": 32, "activation_4": "relu", "dropout_rate_4": 0.0, "dense_units_5": 32, "activation_5": "relu", "dropout_rate_5": 0.0, "dense_units_6": 32, "activation_6": "relu", "dropout_rate_6": 0.0, "dense_units_7": 32, "activation_7": "relu", "dropout_rate_7": 0.0, "dense_units_8": 32, "activation_8": "relu", "dropout_rate_8": 0.0}}, "start_order": ["00", "01", "02", "03", "04", "05", "06", "07", "08", "09", "10", "11", "12", "13", "14", "15", "16", "17", "18", "19"], "end_order": ["00", "01", "02", "03", "04", "05", "06", "07", "08", "09", "10", "11", "12", "13", "14", "15", "16", "17", "18", "19"], "run_times": {"00": 1, "01": 1, "02": 1, "03": 1, "04": 1, "05": 1, "06": 1, "07": 1, "08": 1, "09": 1, "10": 1, "11": 1, "12": 1, "13": 1, "14": 1, "15": 1, "16": 1, "17": 1, "18": 1, "19": 1}, "retry_queue": [], "seed": 5587, "seed_state": 6139, "tried_so_far": ["a512df4f9846d718a2655bdbb1044e1a", "1ebe237c211f540755c6e38ebc77f636", "a8eb0e07c6beea5f1486d3964e05603a", "8d9ee91561f13dacf04fd6c49bfbc734", "a0029caaa2b33af4d809b9f120161ccd", "3a5ddfca47bbe682232e530bdfa42775", "092fb364fcb7d4f6821b23d7c829c6a7", "1c63dcb9e48d98e3975f565e056fb3db", "9a384ff37718af2ddc1935e4d2d75fb8", "496cd1ca9adfcbb8bf2c293256be2510", "586b394d0658858e72cf3d56102ca7ad", "9866f2c7c4f16a7b4075b965ce3d0c9f", "39192f70268bfc3606442bdfd9ef54c2", "91139303f7aba8032ba91586af6dd03f", "ff33f6287b1f049d37a18e14dc54990e", "41c45b1f31d1291b43c41a7d2263207b", "4fe444166626a521b8d61a17536409f3", "a7393a5af1be4bd4f0d149a77d3156bb", "c81c3aa92ae5cb059dd5dbf640c41560", "2a47fc7dd4d6311802c3d4aec83c69b6"], "id_to_hash": {"00": "586b394d0658858e72cf3d56102ca7ad", "01": "1c63dcb9e48d98e3975f565e056fb3db", "02": "c81c3aa92ae5cb059dd5dbf640c41560", "03": "2a47fc7dd4d6311802c3d4aec83c69b6", "04": "9866f2c7c4f16a7b4075b965ce3d0c9f", "05": "3a5ddfca47bbe682232e530bdfa42775", "06": "91139303f7aba8032ba91586af6dd03f", "07": "496cd1ca9adfcbb8bf2c293256be2510", "08": "39192f70268bfc3606442bdfd9ef54c2", "09": "9a384ff37718af2ddc1935e4d2d75fb8", "10": "a512df4f9846d718a2655bdbb1044e1a", "11": "41c45b1f31d1291b43c41a7d2263207b", "12": "a7393a5af1be4bd4f0d149a77d3156bb", "13": "a0029caaa2b33af4d809b9f120161ccd", "14": "8d9ee91561f13dacf04fd6c49bfbc734", "15": "1ebe237c211f540755c6e38ebc77f636", "16": "092fb364fcb7d4f6821b23d7c829c6a7", "17": "4fe444166626a521b8d61a17536409f3", "18": "a8eb0e07c6beea5f1486d3964e05603a", "19": "ff33f6287b1f049d37a18e14dc54990e"}, "display": {"search_start": "2024-10-18T15:44:59.719628", "trial_start": {"00": "2024-10-18T15:44:59.719628", "01": "2024-10-18T15:45:08.086853", "02": "2024-10-18T15:45:19.264984", "03": "2024-10-18T15:45:34.425689", "04": "2024-10-18T15:45:45.375140", "05": "2024-10-18T15:45:55.365130", "06": "2024-10-18T15:46:00.704724", "07": "2024-10-18T15:46:05.196064", "08": "2024-10-18T15:46:22.907628", "09": "2024-10-18T15:46:34.953097", "10": "2024-10-18T15:46:51.902168", "11": "2024-10-18T15:47:03.494371", "12": "2024-10-18T15:47:14.484990", "13": "2024-10-18T15:47:27.241817", "14": "2024-10-18T15:47:35.296776", "15": "2024-10-18T15:47:42.661895", "16": "2024-10-18T15:47:53.205975", "17": "2024-10-18T15:48:04.555706", "18": "2024-10-18T15:48:18.236069", "19": "2024-10-18T15:48:38.384332"}, "trial_number": {"00": 1, "01": 2, "02": 3, "03": 4, "04": 5, "05": 6, "06": 7, "07": 8, "08": 9, "09": 10, "10": 11, "11": 12, "12": 13, "13": 14, "14": 15, "15": 16, "16": 17, "17": 18, "18": 19, "19": 20}}}